setup.cfg
setup.py
py_mailinator.egg-info/PKG-INFO
py_mailinator.egg-info/SOURCES.txt
py_mailinator.egg-info/dependency_links.txt
py_mailinator.egg-info/top_level.txt
pymailinator/__init__.py
pymailinator/_version.py
pymailinator/wrapper.py