Metadata-Version: 1.1
Name: py-mailinator
Version: 0.4.4
Summary: Python API wrapper for mailinator
Home-page: https://github.com/mc706/py-mailinator
Author: Ryan McDevitt
Author-email: mcdevitt.ryan@gmail.com
License: MIT License
Download-URL: https://github.com/mc706/py-mailinator/tarball/0.4
Keywords: mailinator,api,email
Platform: UNKNOWN
Classifier: Programming Language :: Python :: 2.6
Classifier: Programming Language :: Python :: 2.7
Classifier: Programming Language :: Python :: 3
Classifier: Development Status :: 5 - Production/Stable
Classifier: Environment :: Console
Classifier: Intended Audience :: Developers
Classifier: Intended Audience :: Information Technology
Classifier: License :: OSI Approved :: MIT License
Classifier: Operating System :: OS Independent
Classifier: Topic :: Communications :: Email
Classifier: Topic :: Software Development :: Testing
Classifier: Topic :: Utilities
